LICENSE
Makefile
README.md
changelog.md
exodusreader/__init__.py
exodusreader/exodusreader.py
exodusreader-0.1.3.dist-info/LICENSE
exodusreader-0.1.3.dist-info/METADATA
exodusreader-0.1.3.dist-info/WHEEL
exodusreader-0.1.3.dist-info/entry_points.txt
exodusreader-0.1.3.dist-info/RECORD
