Metadata-Version: 2.1
Name: exodusreader
Version: 0.1.3
Summary: Reader for exodus files
Home-page: https://gitlab.dlr.de/fa_sw/peridynamik/exodusreader
License: BSD license
Keywords: exodusReader
Author: Jan-Timo Hesse
Requires-Python: >=3.7,<4.0
Classifier: License :: Other/Proprietary License
Classifier: Programming Language :: Python :: 3
Classifier: Programming Language :: Python :: 3.7
Classifier: Programming Language :: Python :: 3.8
Classifier: Programming Language :: Python :: 3.9
Classifier: Programming Language :: Python :: 3.10
Classifier: Programming Language :: Python :: 3.11
Requires-Dist: netCDF4
Requires-Dist: numpy
Requires-Dist: tomlkit
Project-URL: Repository, https://gitlab.dlr.de/fa_sw/peridynamik/exodusreader
